pyvims/__init__.py
pyvims/__version__.py
pyvims/angles.py
pyvims/camera.py
pyvims/cassini.py
pyvims/constantes.py
pyvims/contour.py
pyvims/coordinates.py
pyvims/corners.py
pyvims/errors.py
pyvims/flyby.py
pyvims/img.py
pyvims/interactive.py
pyvims/interp.py
pyvims/noodle.py
pyvims/pixel.py
pyvims/plot.py
pyvims/quaternions.py
pyvims/qub.py
pyvims/specular.py
pyvims/star.py
pyvims/target.py
pyvims/vars.py
pyvims/vectors.py
pyvims/vertices.py
pyvims/vims.py
pyvims/wget.py
pyvims/wvlns.py
pyvims/calib/__init__.py
pyvims/calib/data.py
pyvims/calib/vars.py
pyvims/calib/data/RC19-VIMS_IR-calibration_multiplier.csv
pyvims/calib/data/RC19-VIMS_IR-solar.csv
pyvims/calib/data/RC19-VIMS_IR-wave_photon_cal.csv
pyvims/calib/data/RC19-VIMS_IR-wavelengths.csv
pyvims/calib/data/RC19-VIMS_VIS-calibration_multiplier.csv
pyvims/calib/data/RC19-VIMS_VIS-solar.csv
pyvims/calib/data/RC19-VIMS_VIS-wave_photon_cal.csv
pyvims/calib/data/RC19-VIMS_VIS-wavelengths.csv
pyvims/data/README.md
pyvims/data/flybys.csv
pyvims/data/titan_npole_stereo_60_all_lakes.png
pyvims/data/titan_npole_stereo_60_jingpo.png
pyvims/data/titan_npole_stereo_60_kraken_inf.png
pyvims/data/titan_npole_stereo_60_kraken_sup.png
pyvims/data/titan_npole_stereo_60_ligeia.png
pyvims/data/titan_npole_stereo_60_other_lakes.png
pyvims/data/titan_npole_stereo_60_punga_kivu.png
pyvims/data/wvlns_ir_shift.csv
pyvims/data/wvlns_std.csv
pyvims/data/maps/Titan_VIMS_ISS.jpg
pyvims/geojson/__init__.py
pyvims/geojson/collection.py
pyvims/geojson/feature.py
pyvims/geojson/geojson.py
pyvims/geojson/geometry.py
pyvims/geol/__init__.py
pyvims/geol/cmap.py
pyvims/geol/data.py
pyvims/geol/titan.py
pyvims/geol/units.py
pyvims/geol/data/Titan_geol_map.png
pyvims/isis/__init__.py
pyvims/isis/errors.py
pyvims/isis/history.py
pyvims/isis/isis.py
pyvims/isis/labels.py
pyvims/isis/tables.py
pyvims/isis/time.py
pyvims/isis/vars.py
pyvims/misc/__init__.py
pyvims/misc/geocube.py
pyvims/misc/greatcircle.py
pyvims/misc/maps.py
pyvims/misc/md5.py
pyvims-1.0.5.dist-info/LICENSE.md
pyvims-1.0.5.dist-info/METADATA
pyvims-1.0.5.dist-info/WHEEL
pyvims-1.0.5.dist-info/top_level.txt
pyvims-1.0.5.dist-info/RECORD
