Metadata-Version: 2.1
Name: pyvims
Version: 1.0.5
Summary: Python package to manipulate the Cassini VIMS data
Home-page: https://github.com/seignovert/pyvims
Author: Benoit Seignovert (LPG-Nantes)
Author-email: pyvims@seignovert.fr
License: BSD
Keywords: cassini,vims,titan
Classifier: Development Status :: 5 - Production/Stable
Classifier: Intended Audience :: Developers
Classifier: Intended Audience :: Science/Research
Classifier: License :: OSI Approved :: BSD License
Classifier: Natural Language :: English
Classifier: Programming Language :: Python
Classifier: Programming Language :: Python :: 3.7
Classifier: Programming Language :: Python :: 3.8
Classifier: Programming Language :: Python :: 3.9
Classifier: Programming Language :: Python :: 3.10
Classifier: Topic :: Scientific/Engineering
Classifier: Topic :: Scientific/Engineering :: Astronomy
Classifier: Topic :: Scientific/Engineering :: Atmospheric Science
Requires-Python: >=3.6
License-File: LICENSE.md
Requires-Dist: numpy>=1.17
Requires-Dist: matplotlib>=3.1
Requires-Dist: Pillow
Requires-Dist: scipy
Requires-Dist: tqdm
Requires-Dist: requests
Requires-Dist: pvl
